{"numFailedTestSuites":0,"numFailedTests":0,"numPassedTestSuites":9,"numPassedTests":21,"numPendingTestSuites":0,"numPendingTests":0,"numRuntimeErrorTestSuites":0,"numTodoTests":0,"numTotalTestSuites":9,"numTotalTests":21,"openHandles":[],"snapshot":{"added":0,"didUpdate":false,"failure":false,"filesAdded":0,"filesRemoved":0,"filesRemovedList":[],"filesUnmatched":0,"filesUpdated":0,"matched":0,"total":0,"unchecked":0,"uncheckedKeysByFile":[],"unmatched":0,"updated":0},"startTime":1760012191671,"success":true,"testResults":[{"assertionResults":[{"ancestorTitles":["Molecules/RadioField","Playground"],"duration":2658,"failureDetails":[],"failureMessages":[],"fullName":"Molecules/RadioField Playground smoke-test","invocations":1,"location":null,"numPassingAsserts":0,"retryReasons":[],"status":"passed","title":"smoke-test"},{"ancestorTitles":["Molecules/RadioField","WithError"],"duration":300,"failureDetails":[],"failureMessages":[],"fullName":"Molecules/RadioField WithError smoke-test","invocations":1,"location":null,"numPassingAsserts":0,"retryReasons":[],"status":"passed","title":"smoke-test"}],"endTime":1760012205519,"message":"","name":"/Home1/project/web-platform/frontend/src/stories/RadioField.stories.tsx","startTime":1760012195755,"status":"passed","summary":""},{"assertionResults":[{"ancestorTitles":["Molecules/Card","Overview"],"duration":2583,"failureDetails":[],"failureMessages":[],"fullName":"Molecules/Card Overview smoke-test","invocations":1,"location":null,"numPassingAsserts":0,"retryReasons":[],"status":"passed","title":"smoke-test"},{"ancestorTitles":["Molecules/Card","Highlighted"],"duration":296,"failureDetails":[],"failureMessages":[],"fullName":"Molecules/Card Highlighted smoke-test","invocations":1,"location":null,"numPassingAsserts":0,"retryReasons":[],"status":"passed","title":"smoke-test"}],"endTime":1760012205523,"message":"","name":"/Home1/project/web-platform/frontend/src/stories/Card.stories.tsx","startTime":1760012195611,"status":"passed","summary":""},{"assertionResults":[{"ancestorTitles":["Atoms/Button","Playground"],"duration":3015,"failureDetails":[],"failureMessages":[],"fullName":"Atoms/Button Playground smoke-test","invocations":1,"location":null,"numPassingAsserts":0,"retryReasons":[],"status":"passed","title":"smoke-test"},{"ancestorTitles":["Atoms/Button","WithIcons"],"duration":194,"failureDetails":[],"failureMessages":[],"fullName":"Atoms/Button WithIcons smoke-test","invocations":1,"location":null,"numPassingAsserts":0,"retryReasons":[],"status":"passed","title":"smoke-test"},{"ancestorTitles":["Atoms/Button","Loading"],"duration":171,"failureDetails":[],"failureMessages":[],"fullName":"Atoms/Button Loading smoke-test","invocations":1,"location":null,"numPassingAsserts":0,"retryReasons":[],"status":"passed","title":"smoke-test"},{"ancestorTitles":["Atoms/Button","ThemeSampler"],"duration":141,"failureDetails":[],"failureMessages":[],"fullName":"Atoms/Button ThemeSampler smoke-test","invocations":1,"location":null,"numPassingAsserts":0,"retryReasons":[],"status":"passed","title":"smoke-test"}],"endTime":1760012205721,"message":"","name":"/Home1/project/web-platform/frontend/src/stories/Button.stories.tsx","startTime":1760012195203,"status":"passed","summary":""},{"assertionResults":[{"ancestorTitles":["Atoms/Checkbox","Playground"],"duration":1341,"failureDetails":[],"failureMessages":[],"fullName":"Atoms/Checkbox Playground smoke-test","invocations":1,"location":null,"numPassingAsserts":0,"retryReasons":[],"status":"passed","title":"smoke-test"},{"ancestorTitles":["Atoms/Checkbox","WithLabel"],"duration":206,"failureDetails":[],"failureMessages":[],"fullName":"Atoms/Checkbox WithLabel smoke-test","invocations":1,"location":null,"numPassingAsserts":0,"retryReasons":[],"status":"passed","title":"smoke-test"}],"endTime":1760012208613,"message":"","name":"/Home1/project/web-platform/frontend/src/stories/Checkbox.stories.tsx","startTime":1760012205559,"status":"passed","summary":""},{"assertionResults":[{"ancestorTitles":["Atoms/Label","Playground"],"duration":1350,"failureDetails":[],"failureMessages":[],"fullName":"Atoms/Label Playground smoke-test","invocations":1,"location":null,"numPassingAsserts":0,"retryReasons":[],"status":"passed","title":"smoke-test"},{"ancestorTitles":["Atoms/Label","Small"],"duration":188,"failureDetails":[],"failureMessages":[],"fullName":"Atoms/Label Small smoke-test","invocations":1,"location":null,"numPassingAsserts":0,"retryReasons":[],"status":"passed","title":"smoke-test"}],"endTime":1760012208964,"message":"","name":"/Home1/project/web-platform/frontend/src/stories/Label.stories.tsx","startTime":1760012205741,"status":"passed","summary":""},{"assertionResults":[{"ancestorTitles":["Atoms/Input","Playground"],"duration":1664,"failureDetails":[],"failureMessages":[],"fullName":"Atoms/Input Playground smoke-test","invocations":1,"location":null,"numPassingAsserts":0,"retryReasons":[],"status":"passed","title":"smoke-test"},{"ancestorTitles":["Atoms/Input","WithAdornment"],"duration":175,"failureDetails":[],"failureMessages":[],"fullName":"Atoms/Input WithAdornment smoke-test","invocations":1,"location":null,"numPassingAsserts":0,"retryReasons":[],"status":"passed","title":"smoke-test"},{"ancestorTitles":["Atoms/Input","Invalid"],"duration":162,"failureDetails":[],"failureMessages":[],"fullName":"Atoms/Input Invalid smoke-test","invocations":1,"location":null,"numPassingAsserts":0,"retryReasons":[],"status":"passed","title":"smoke-test"}],"endTime":1760012209200,"message":"","name":"/Home1/project/web-platform/frontend/src/stories/Input.stories.tsx","startTime":1760012205556,"status":"passed","summary":""},{"assertionResults":[{"ancestorTitles":["Molecules/CheckboxField","Playground"],"duration":1400,"failureDetails":[],"failureMessages":[],"fullName":"Molecules/CheckboxField Playground smoke-test","invocations":1,"location":null,"numPassingAsserts":0,"retryReasons":[],"status":"passed","title":"smoke-test"},{"ancestorTitles":["Molecules/CheckboxField","RequiredWithError"],"duration":144,"failureDetails":[],"failureMessages":[],"fullName":"Molecules/CheckboxField RequiredWithError smoke-test","invocations":1,"location":null,"numPassingAsserts":0,"retryReasons":[],"status":"passed","title":"smoke-test"}],"endTime":1760012211466,"message":"","name":"/Home1/project/web-platform/frontend/src/stories/CheckboxField.stories.tsx","startTime":1760012208639,"status":"passed","summary":""},{"assertionResults":[{"ancestorTitles":["Atoms/Toggle","Playground"],"duration":1010,"failureDetails":[],"failureMessages":[],"fullName":"Atoms/Toggle Playground smoke-test","invocations":1,"location":null,"numPassingAsserts":0,"retryReasons":[],"status":"passed","title":"smoke-test"},{"ancestorTitles":["Atoms/Toggle","WithIcons"],"duration":100,"failureDetails":[],"failureMessages":[],"fullName":"Atoms/Toggle WithIcons smoke-test","invocations":1,"location":null,"numPassingAsserts":0,"retryReasons":[],"status":"passed","title":"smoke-test"}],"endTime":1760012211693,"message":"","name":"/Home1/project/web-platform/frontend/src/stories/Toggle.stories.tsx","startTime":1760012209264,"status":"passed","summary":""},{"assertionResults":[{"ancestorTitles":["Atoms/Radio","Playground"],"duration":1083,"failureDetails":[],"failureMessages":[],"fullName":"Atoms/Radio Playground smoke-test","invocations":1,"location":null,"numPassingAsserts":0,"retryReasons":[],"status":"passed","title":"smoke-test"},{"ancestorTitles":["Atoms/Radio","WithField"],"duration":261,"failureDetails":[],"failureMessages":[],"fullName":"Atoms/Radio WithField smoke-test","invocations":1,"location":null,"numPassingAsserts":0,"retryReasons":[],"status":"passed","title":"smoke-test"}],"endTime":1760012211686,"message":"","name":"/Home1/project/web-platform/frontend/src/stories/Radio.stories.tsx","startTime":1760012208990,"status":"passed","summary":""}],"wasInterrupted":false}
